core/__init__.py
core/main.py
tests/__init__.py
tests/test_tree.py
codebasedutils-0.0.1.dist-info/METADATA
codebasedutils-0.0.1.dist-info/WHEEL
codebasedutils-0.0.1.dist-info/entry_points.txt
codebasedutils-0.0.1.dist-info/top_level.txt
codebasedutils-0.0.1.dist-info/RECORD
