Metadata-Version: 2.1
Name: codebasedutils
Version: 0.0.1
Summary: CodebasedUtils is a versatile CLI tool designed to supercharge your developer workflow.
Home-page: https://github.com/cybrvybe/CodebasedUtils
Author: Alex Figueroa
Author-email: alexfigueroa.solutions@gmail.com
Classifier: Programming Language :: Python :: 3
Classifier: License :: OSI Approved :: MIT License
Classifier: Operating System :: OS Independent
Requires-Python: >=3.6
Requires-Dist: click ==8.1.7
Requires-Dist: colorama ==0.4.6
Requires-Dist: iniconfig ==2.0.0
Requires-Dist: packaging ==23.2
Requires-Dist: pluggy ==1.3.0
Requires-Dist: pyperclip ==1.8.2
Requires-Dist: pytest ==7.4.2
